plotstats/__init__.py
plotstats/plotstats.py
plotstats-1.0.14.dist-info/LICENSE
plotstats-1.0.14.dist-info/METADATA
plotstats-1.0.14.dist-info/WHEEL
plotstats-1.0.14.dist-info/top_level.txt
plotstats-1.0.14.dist-info/RECORD
