Metadata-Version: 2.1
Name: plotstats
Version: 1.0.14
Summary: A basic module for statistic works!
Author: Amirreza Soltani
Author-email: charleswestmorelandPB1@gmail.com
Keywords: python,statistics,visualization,data grouping,plenty,relative plenty,batch centers
Classifier: Programming Language :: Python :: 3
Classifier: License :: OSI Approved :: MIT License
Classifier: Operating System :: Unix
Classifier: Operating System :: MacOS :: MacOS X
Classifier: Operating System :: Microsoft :: Windows
Requires-Python: >=3.6
License-File: LICENSE
Requires-Dist: numpy
Requires-Dist: pandas
Requires-Dist: matplotlib
